cctxpro/__init__.py
cctxpro-1.0.0.dist-info/METADATA
cctxpro-1.0.0.dist-info/WHEEL
cctxpro-1.0.0.dist-info/top_level.txt
cctxpro-1.0.0.dist-info/RECORD
